pydvdcss/__init__.py
pydvdcss/dvdcss.py
pydvdcss/exceptions.py
pydvdcss-1.4.0.dist-info/LICENSE
pydvdcss-1.4.0.dist-info/METADATA
pydvdcss-1.4.0.dist-info/WHEEL
pydvdcss-1.4.0.dist-info/RECORD
